{
	"name": "Handmann",
	"description": "Nobody knows why Handmann look like human hands. There are reports of people having their hands eaten and replaced by Handmann, which in the end take over the hosts mind.",
	"img": "./res/pacratcher/handmann.png",
	"width": 159,
	"height": 186.25,
	"health": 95,
	"attacks": {
		"Handschlag": {
			"description": "Traditional greeting between Handmanns",
			"cost": 1,
			"dmg": 10,
			"speed": 0.95,
			"accuracy": 0.8
		},
		"Schnick-Schnack-Schnuck": {
			"description": "Advanced Handmann fighting styles few can master",
			"cost": 4,
			"dmg": 40,
			"speed": 0.45,
			"accuracy": 0.66
		}
	},
	"accuracy": 0.85,
	"speed": 5,
	"card": {
		"borderColor": "#D4AF37",
		"background": "#232323",
		"icons": {
			"speed": "./res/icons/Schuh.png",
			"dmg": "./res/icons/Schwert.png",
			"accuracy": "./res/icons/Ziel.png"
		}
	}
}
